pi_dht_webthing/__init__.py
pi_dht_webthing/app.py
pi_dht_webthing/dht_webthing.py
pi_dht_webthing-0.1.2.dist-info/LICENSE
pi_dht_webthing-0.1.2.dist-info/METADATA
pi_dht_webthing-0.1.2.dist-info/WHEEL
pi_dht_webthing-0.1.2.dist-info/entry_points.txt
pi_dht_webthing-0.1.2.dist-info/top_level.txt
pi_dht_webthing-0.1.2.dist-info/RECORD
