Metadata-Version: 2.1
Name: pi-dht-webthing
Version: 0.1.2
Summary: A web connected DHT sensor reading temperature and humidity values on Raspberry Pi
Home-page: https://github.com/grro/pi_dht_webthing
Author: Gregor Roth
Author-email: gregor.roth@web.de
License: MIT
Keywords: webthings,dht,dht11,dht22,home automation,humidity sensor,temperature sensor,raspberry,pi
Platform: UNKNOWN
Classifier: Programming Language :: Python :: 3
Classifier: License :: OSI Approved :: Apache Software License
Classifier: Operating System :: OS Independent
Classifier: Development Status :: 3 - Alpha
Requires-Dist: webthing ==0.15.0
Requires-Dist: Adafruit-DHT ==1.4.0
